{
    "comments":["A list of the bird species recognized by Lintulista."],
				
	"birds":
	[
		{"species":"Kyhmyjoutsen","order":"Sorsalinnut","family":"Sorsat"},
		{"species":"Pikkujoutsen","order":"Sorsalinnut","family":"Sorsat"},
		{"species":"Laulujoutsen","order":"Sorsalinnut","family":"Sorsat"},
		{"species":"Metsähanhi","order":"Sorsalinnut","family":"Sorsat"},
		{"species":"Lyhytnokkahanhi","order":"Sorsalinnut","family":"Sorsat"},
		{"species":"Tundrahanhi","order":"Sorsalinnut","family":"Sorsat"},
		{"species":"Kiljuhanhi","order":"Sorsalinnut","family":"Sorsat"},
		{"species":"Merihanhi","order":"Sorsalinnut","family":"Sorsat"},
		{"species":"Lumihanhi","order":"Sorsalinnut","family":"Sorsat"},
		{"species":"Kanadanhanhi","order":"Sorsalinnut","family":"Sorsat"},
		{"species":"Pikkukanadanhanhi","order":"Sorsalinnut","family":"Sorsat"},
		{"species":"Valkoposkihanhi","order":"Sorsalinnut","family":"Sorsat"},
		{"species":"Sepelhanhi","order":"Sorsalinnut","family":"Sorsat"},
		{"species":"Punakaulahanhi","order":"Sorsalinnut","family":"Sorsat"},
		{"species":"Ruostesorsa","order":"Sorsalinnut","family":"Sorsat"},
		{"species":"Ristisorsa","order":"Sorsalinnut","family":"Sorsat"},
		{"species":"Mandariinisorsa","order":"Sorsalinnut","family":"Sorsat"},
		{"species":"Haapana","order":"Sorsalinnut","family":"Sorsat"},
		{"species":"Amerikanhaapana","order":"Sorsalinnut","family":"Sorsat"},
		{"species":"Harmaasorsa","order":"Sorsalinnut","family":"Sorsat"},
		{"species":"Tavi","order":"Sorsalinnut","family":"Sorsat"},
		{"species":"Amerikantavi","order":"Sorsalinnut","family":"Sorsat"},
		{"species":"Sinisorsa","order":"Sorsalinnut","family":"Sorsat"},
		{"species":"Nokisorsa","order":"Sorsalinnut","family":"Sorsat"},
		{"species":"Jouhisorsa","order":"Sorsalinnut","family":"Sorsat"},
		{"species":"Heinätavi","order":"Sorsalinnut","family":"Sorsat"},
		{"species":"Sinisiipitavi","order":"Sorsalinnut","family":"Sorsat"},
		{"species":"Lapasorsa","order":"Sorsalinnut","family":"Sorsat"},
		{"species":"Punapäänarsku","order":"Sorsalinnut","family":"Sorsat"},
		{"species":"Punasotka","order":"Sorsalinnut","family":"Sorsat"},
		{"species":"Amerikantukkasotka","order":"Sorsalinnut","family":"Sorsat"},
		{"species":"Ruskosotka","order":"Sorsalinnut","family":"Sorsat"},
		{"species":"Tukkasotka","order":"Sorsalinnut","family":"Sorsat"},
		{"species":"Lapasotka","order":"Sorsalinnut","family":"Sorsat"},
		{"species":"Pikkulapasotka","order":"Sorsalinnut","family":"Sorsat"},
		{"species":"Haahka","order":"Sorsalinnut","family":"Sorsat"},
		{"species":"Kyhmyhaahka","order":"Sorsalinnut","family":"Sorsat"},
		{"species":"Allihaahka","order":"Sorsalinnut","family":"Sorsat"},
		{"species":"Virta-alli","order":"Sorsalinnut","family":"Sorsat"},
		{"species":"Alli","order":"Sorsalinnut","family":"Sorsat"},
		{"species":"Mustalintu","order":"Sorsalinnut","family":"Sorsat"},
		{"species":"Amerikanmustalintu","order":"Sorsalinnut","family":"Sorsat"},
		{"species":"Pilkkaniska","order":"Sorsalinnut","family":"Sorsat"},
		{"species":"Pilkkasiipi","order":"Sorsalinnut","family":"Sorsat"},
		{"species":"Kyhmypilkkasiipi","order":"Sorsalinnut","family":"Sorsat"},
		{"species":"Telkkä","order":"Sorsalinnut","family":"Sorsat"},
		{"species":"Uivelo","order":"Sorsalinnut","family":"Sorsat"},
		{"species":"Tukkakoskelo","order":"Sorsalinnut","family":"Sorsat"},
		{"species":"Isokoskelo","order":"Sorsalinnut","family":"Sorsat"},
		{"species":"Kuparisorsa","order":"Sorsalinnut","family":"Sorsat"},
		{"species":"Viiriäinen","order":"Kanalinnut","family":"Aitokanat"},
		{"species":"Pyy","order":"Kanalinnut","family":"Aitokanat"},
		{"species":"Riekko","order":"Kanalinnut","family":"Aitokanat"},
		{"species":"Kiiruna","order":"Kanalinnut","family":"Aitokanat"},
		{"species":"Teeri","order":"Kanalinnut","family":"Aitokanat"},
		{"species":"Metso","order":"Kanalinnut","family":"Aitokanat"},
		{"species":"Peltopyy","order":"Kanalinnut","family":"Aitokanat"},
		{"species":"Fasaani","order":"Kanalinnut","family":"Aitokanat"},
		{"species":"Kaakkuri","order":"Kuikkalinnut","family":"Kuikat"},
		{"species":"Kuikka","order":"Kuikkalinnut","family":"Kuikat"},
		{"species":"Tundrakuikka","order":"Kuikkalinnut","family":"Kuikat"},
		{"species":"Amerikanjääkuikka","order":"Kuikkalinnut","family":"Kuikat"},
		{"species":"Jääkuikka","order":"Kuikkalinnut","family":"Kuikat"},
		{"species":"Pikku-uikku","order":"Uikkulinnut","family":"Uikut"},
		{"species":"Silkkiuikku","order":"Uikkulinnut","family":"Uikut"},
		{"species":"Härkälintu","order":"Uikkulinnut","family":"Uikut"},
		{"species":"Mustakurkku-uikku","order":"Uikkulinnut","family":"Uikut"},
		{"species":"Mustakaulauikku","order":"Uikkulinnut","family":"Uikut"},
		{"species":"Myrskylintu","order":"Ulappalinnut","family":"Ulappaliitäjät"},
		{"species":"Nokiliitäjä","order":"Ulappalinnut","family":"Ulappaliitäjät"},
		{"species":"Pikkuliitäjä","order":"Ulappalinnut","family":"Ulappaliitäjät"},
		{"species":"Merikeiju","order":"Ulappalinnut","family":"Ulappakeijut"},
		{"species":"Myrskykeiju","order":"Ulappalinnut","family":"Ulappakeijut"},
		{"species":"Madeirankeiju","order":"Ulappalinnut","family":"Ulappakeijut"},
		{"species":"Suula","order":"Pelikaanilinnut","family":"Suulat"},
		{"species":"Merimetso","order":"Pelikaanilinnut","family":"Merimetsot"},
		{"species":"Karimetso","order":"Pelikaanilinnut","family":"Merimetsot"},
		{"species":"Pelikaani","order":"Pelikaanilinnut","family":"Pelikaanit"},
		{"species":"Kaulushaikara","order":"Haikaralinnut","family":"Haikarat"},
		{"species":"Pikkuhaikara","order":"Haikaralinnut","family":"Haikarat"},
		{"species":"Yöhaikara","order":"Haikaralinnut","family":"Haikarat"},
		{"species":"Rääkkähaikara","order":"Haikaralinnut","family":"Haikarat"},
		{"species":"Lehmähaikara","order":"Haikaralinnut","family":"Haikarat"},
		{"species":"Silkkihaikara","order":"Haikaralinnut","family":"Haikarat"},
		{"species":"Jalohaikara","order":"Haikaralinnut","family":"Haikarat"},
		{"species":"Harmaahaikara","order":"Haikaralinnut","family":"Haikarat"},
		{"species":"Ruskohaikara","order":"Haikaralinnut","family":"Haikarat"},
		{"species":"Mustahaikara","order":"Haikaralinnut","family":"Kattohaikarat"},
		{"species":"Kattohaikara","order":"Haikaralinnut","family":"Kattohaikarat"},
		{"species":"Pronssi-iibis","order":"Haikaralinnut","family":"Iibikset"},
		{"species":"Kapustahaikara","order":"Haikaralinnut","family":"Iibikset"},
		{"species":"Mehiläishaukka","order":"Päiväpetolinnut","family":"Haukat"},
		{"species":"Haarahaukka","order":"Päiväpetolinnut","family":"Haukat"},
		{"species":"Isohaarahaukka","order":"Päiväpetolinnut","family":"Haukat"},
		{"species":"Aromerikotka","order":"Päiväpetolinnut","family":"Haukat"},
		{"species":"Merikotka","order":"Päiväpetolinnut","family":"Haukat"},
		{"species":"Pikkukorppikotka","order":"Päiväpetolinnut","family":"Haukat"},
		{"species":"Hanhikorppikotka","order":"Päiväpetolinnut","family":"Haukat"},
		{"species":"Munkkikorppikotka","order":"Päiväpetolinnut","family":"Haukat"},
		{"species":"Käärmekotka","order":"Päiväpetolinnut","family":"Haukat"},
		{"species":"Ruskosuohaukka","order":"Päiväpetolinnut","family":"Haukat"},
		{"species":"Sinisuohaukka","order":"Päiväpetolinnut","family":"Haukat"},
		{"species":"Arosuohaukka","order":"Päiväpetolinnut","family":"Haukat"},
		{"species":"Niittysuohaukka","order":"Päiväpetolinnut","family":"Haukat"},
		{"species":"Kanahaukka","order":"Päiväpetolinnut","family":"Haukat"},
		{"species":"Varpushaukka","order":"Päiväpetolinnut","family":"Haukat"},
		{"species":"Hiirihaukka","order":"Päiväpetolinnut","family":"Haukat"},
		{"species":"Arohiirihaukka","order":"Päiväpetolinnut","family":"Haukat"},
		{"species":"Piekana","order":"Päiväpetolinnut","family":"Haukat"},
		{"species":"Kiljukotka","order":"Päiväpetolinnut","family":"Haukat"},
		{"species":"Pikkukiljukotka","order":"Päiväpetolinnut","family":"Haukat"},
		{"species":"Pikkukotka","order":"Päiväpetolinnut","family":"Haukat"},
		{"species":"Maakotka","order":"Päiväpetolinnut","family":"Haukat"},
		{"species":"Arokotka","order":"Päiväpetolinnut","family":"Haukat"},
		{"species":"Keisarikotka","order":"Päiväpetolinnut","family":"Haukat"},
		{"species":"Sääksi","order":"Päiväpetolinnut","family":"Sääkset"},
		{"species":"Pikkutuulihaukka","order":"Jalohaukkalinnut","family":"Jalohaukat"},
		{"species":"Tuulihaukka","order":"Jalohaukkalinnut","family":"Jalohaukat"},
		{"species":"Punajalkahaukka","order":"Jalohaukkalinnut","family":"Jalohaukat"},
		{"species":"Ampuhaukka","order":"Jalohaukkalinnut","family":"Jalohaukat"},
		{"species":"Nuolihaukka","order":"Jalohaukkalinnut","family":"Jalohaukat"},
		{"species":"Välimerenhaukka","order":"Jalohaukkalinnut","family":"Jalohaukat"},
		{"species":"Aavikkohaukka","order":"Jalohaukkalinnut","family":"Jalohaukat"},
		{"species":"Tunturihaukka","order":"Jalohaukkalinnut","family":"Jalohaukat"},
		{"species":"Muuttohaukka","order":"Jalohaukkalinnut","family":"Jalohaukat"},
		{"species":"Luhtakana","order":"Kurkilinnut","family":"Rantakanat"},
		{"species":"Luhtahuitti","order":"Kurkilinnut","family":"Rantakanat"},
		{"species":"Pikkuhuitti","order":"Kurkilinnut","family":"Rantakanat"},
		{"species":"Kääpiöhuitti","order":"Kurkilinnut","family":"Rantakanat"},
		{"species":"Ruisrääkkä","order":"Kurkilinnut","family":"Rantakanat"},
		{"species":"Liejukana","order":"Kurkilinnut","family":"Rantakanat"},
		{"species":"Kurnuliejukana","order":"Kurkilinnut","family":"Rantakanat"},
		{"species":"Nokikana","order":"Kurkilinnut","family":"Rantakanat"},
		{"species":"Kurki","order":"Kurkilinnut","family":"Kurjet"},
		{"species":"Hietakurki","order":"Kurkilinnut","family":"Kurjet"},
		{"species":"Neitokurki","order":"Kurkilinnut","family":"Kurjet"},
		{"species":"Pikkutrappi","order":"Kurkilinnut","family":"Trapit"},
		{"species":"Idänkaulustrappi","order":"Kurkilinnut","family":"Trapit"},
		{"species":"Isotrappi","order":"Kurkilinnut","family":"Trapit"},
		{"species":"Paksujalka","order":"Rantalinnut","family":"Paksujalat"},
		{"species":"Pitkäjalka","order":"Rantalinnut","family":"Avosetit"},
		{"species":"Avosetti","order":"Rantalinnut","family":"Avosetit"},
		{"species":"Meriharakka","order":"Rantalinnut","family":"Meriharakat"},
		{"species":"Siperiankurmitsa","order":"Rantalinnut","family":"Kurmitsat"},
		{"species":"Amerikankurmitsa","order":"Rantalinnut","family":"Kurmitsat"},
		{"species":"Kapustarinta","order":"Rantalinnut","family":"Kurmitsat"},
		{"species":"Tundrakurmitsa","order":"Rantalinnut","family":"Kurmitsat"},
		{"species":"Arohyyppä","order":"Rantalinnut","family":"Kurmitsat"},
		{"species":"Suohyyppä","order":"Rantalinnut","family":"Kurmitsat"},
		{"species":"Töyhtöhyyppä","order":"Rantalinnut","family":"Kurmitsat"},
		{"species":"Pikkutylli","order":"Rantalinnut","family":"Kurmitsat"},
		{"species":"Tylli","order":"Rantalinnut","family":"Kurmitsat"},
		{"species":"Mustajalkatylli","order":"Rantalinnut","family":"Kurmitsat"},
		{"species":"Ylänkötylli","order":"Rantalinnut","family":"Kurmitsat"},
		{"species":"Aavikkotylli","order":"Rantalinnut","family":"Kurmitsat"},
		{"species":"Kaspiantylli","order":"Rantalinnut","family":"Kurmitsat"},
		{"species":"Gobintylli","order":"Rantalinnut","family":"Kurmitsat"},
		{"species":"Keräkurmitsa","order":"Rantalinnut","family":"Kurmitsat"},
		{"species":"Preeriakahlaaja","order":"Rantalinnut","family":"Kurpat"},
		{"species":"Taigakuovi","order":"Rantalinnut","family":"Kurpat"},
		{"species":"Pikkukuovi","order":"Rantalinnut","family":"Kurpat"},
		{"species":"Kuovi","order":"Rantalinnut","family":"Kurpat"},
		{"species":"Mustapyrstökuiri","order":"Rantalinnut","family":"Kurpat"},
		{"species":"Punakuiri","order":"Rantalinnut","family":"Kurpat"},
		{"species":"Karikukko","order":"Rantalinnut","family":"Kurpat"},
		{"species":"Isosirri","order":"Rantalinnut","family":"Kurpat"},
		{"species":"Suokukko","order":"Rantalinnut","family":"Kurpat"},
		{"species":"Suippopyrstösirri","order":"Rantalinnut","family":"Kurpat"},
		{"species":"Jänkäsirriäinen","order":"Rantalinnut","family":"Kurpat"},
		{"species":"Kuovisirri","order":"Rantalinnut","family":"Kurpat"},
		{"species":"Pitkäkoipisirri","order":"Rantalinnut","family":"Kurpat"},
		{"species":"Rusokaulasirri","order":"Rantalinnut","family":"Kurpat"},
		{"species":"Siperiansirri","order":"Rantalinnut","family":"Kurpat"},
		{"species":"Lapinsirri","order":"Rantalinnut","family":"Kurpat"},
		{"species":"Pulmussirri","order":"Rantalinnut","family":"Kurpat"},
		{"species":"Suosirri","order":"Rantalinnut","family":"Kurpat"},
		{"species":"Merisirri","order":"Rantalinnut","family":"Kurpat"},
		{"species":"Eskimosirri","order":"Rantalinnut","family":"Kurpat"},
		{"species":"Pikkusirri","order":"Rantalinnut","family":"Kurpat"},
		{"species":"Valkoperäsirri","order":"Rantalinnut","family":"Kurpat"},
		{"species":"Amerikansirri","order":"Rantalinnut","family":"Kurpat"},
		{"species":"Tundravikla","order":"Rantalinnut","family":"Kurpat"},
		{"species":"Palsasirri","order":"Rantalinnut","family":"Kurpat"},
		{"species":"Amerikanvesipääsky","order":"Rantalinnut","family":"Kurpat"},
		{"species":"Vesipääsky","order":"Rantalinnut","family":"Kurpat"},
		{"species":"Isovesipääsky","order":"Rantalinnut","family":"Kurpat"},
		{"species":"Rantakurvi","order":"Rantalinnut","family":"Kurpat"},
		{"species":"Rantasipi","order":"Rantalinnut","family":"Kurpat"},
		{"species":"Amerikansipi","order":"Rantalinnut","family":"Kurpat"},
		{"species":"Metsäviklo","order":"Rantalinnut","family":"Kurpat"},
		{"species":"Mustaviklo","order":"Rantalinnut","family":"Kurpat"},
		{"species":"Valkoviklo","order":"Rantalinnut","family":"Kurpat"},
		{"species":"Keltajalkaviklo","order":"Rantalinnut","family":"Kurpat"},
		{"species":"Preeriaviklo","order":"Rantalinnut","family":"Kurpat"},
		{"species":"Lampiviklo","order":"Rantalinnut","family":"Kurpat"},
		{"species":"Liro","order":"Rantalinnut","family":"Kurpat"},
		{"species":"Punajalkaviklo","order":"Rantalinnut","family":"Kurpat"},
		{"species":"Jänkäkurppa","order":"Rantalinnut","family":"Kurpat"},
		{"species":"Tundrakurppelo","order":"Rantalinnut","family":"Kurpat"},
		{"species":"Lehtokurppa","order":"Rantalinnut","family":"Kurpat"},
		{"species":"Taivaanvuohi","order":"Rantalinnut","family":"Kurpat"},
		{"species":"Amerikantaivaanvuohi","order":"Rantalinnut","family":"Kurpat"},
		{"species":"Heinäkurppa","order":"Rantalinnut","family":"Kurpat"},
		{"species":"Siperiankurppa","order":"Rantalinnut","family":"Kurpat"},
		{"species":"Pääskykahlaaja","order":"Rantalinnut","family":"Pääskykahlaajat"},
		{"species":"Aasianpääskykahlaaja","order":"Rantalinnut","family":"Pääskykahlaajat"},
		{"species":"Aropääskykahlaaja","order":"Rantalinnut","family":"Pääskykahlaajat"},
		{"species":"Aavikkojuoksija","order":"Rantalinnut","family":"Pääskykahlaajat"},
		{"species":"Leveäpyrstökihu","order":"Rantalinnut","family":"Kihut"},
		{"species":"Merikihu","order":"Rantalinnut","family":"Kihut"},
		{"species":"Tunturikihu","order":"Rantalinnut","family":"Kihut"},
		{"species":"Isokihu","order":"Rantalinnut","family":"Kihut"},
		{"species":"Lunni","order":"Rantalinnut","family":"Ruokit"},
		{"species":"Riskilä","order":"Rantalinnut","family":"Ruokit"},
		{"species":"Ruokki","order":"Rantalinnut","family":"Ruokit"},
		{"species":"Pikkuruokki","order":"Rantalinnut","family":"Ruokit"},
		{"species":"Etelänkiisla","order":"Rantalinnut","family":"Ruokit"},
		{"species":"Pohjankiisla","order":"Rantalinnut","family":"Ruokit"},
		{"species":"Pikkutiira","order":"Rantalinnut","family":"Tiirat"},
		{"species":"Hietatiira","order":"Rantalinnut","family":"Tiirat"},
		{"species":"Räyskä","order":"Rantalinnut","family":"Tiirat"},
		{"species":"Valkoposkitiira","order":"Rantalinnut","family":"Tiirat"},
		{"species":"Mustatiira","order":"Rantalinnut","family":"Tiirat"},
		{"species":"Valkosiipitiira","order":"Rantalinnut","family":"Tiirat"},
		{"species":"Riuttatiira","order":"Rantalinnut","family":"Tiirat"},
		{"species":"Kalatiira","order":"Rantalinnut","family":"Tiirat"},
		{"species":"Lapintiira","order":"Rantalinnut","family":"Tiirat"},
		{"species":"Pikkulokki","order":"Rantalinnut","family":"Lokit"},
		{"species":"Ruusulokki","order":"Rantalinnut","family":"Lokit"},
		{"species":"Jäälokki","order":"Rantalinnut","family":"Lokit"},
		{"species":"Tiiralokki","order":"Rantalinnut","family":"Lokit"},
		{"species":"Pikkukajava","order":"Rantalinnut","family":"Lokit"},
		{"species":"Kaitanokkalokki","order":"Rantalinnut","family":"Lokit"},
		{"species":"Naurulokki","order":"Rantalinnut","family":"Lokit"},
		{"species":"Nokisiipilokki","order":"Rantalinnut","family":"Lokit"},
		{"species":"Preerianaurulokki","order":"Rantalinnut","family":"Lokit"},
		{"species":"Välimerenlokki","order":"Rantalinnut","family":"Lokit"},
		{"species":"Mustanmerenlokki","order":"Rantalinnut","family":"Lokit"},
		{"species":"Kalalokki","order":"Rantalinnut","family":"Lokit"},
		{"species":"Selkälokki","order":"Rantalinnut","family":"Lokit"},
		{"species":"Harmaalokki","order":"Rantalinnut","family":"Lokit"},
		{"species":"Aroharmaalokki","order":"Rantalinnut","family":"Lokit"},
		{"species":"Etelänharmaalokki","order":"Rantalinnut","family":"Lokit"},
		{"species":"Ohotanlokki","order":"Rantalinnut","family":"Lokit"},
		{"species":"Grönlanninlokki","order":"Rantalinnut","family":"Lokit"},
		{"species":"Isolokki","order":"Rantalinnut","family":"Lokit"},
		{"species":"Merilokki","order":"Rantalinnut","family":"Lokit"},
		{"species":"Arokyyhky","order":"Hietakanalinnut","family":"Hietakyyhkyt"},
		{"species":"Kalliokyyhky","order":"Kyyhkylinnut","family":"Kyyhkyt"},
		{"species":"Uuttukyyhky","order":"Kyyhkylinnut","family":"Kyyhkyt"},
		{"species":"Sepelkyyhky","order":"Kyyhkylinnut","family":"Kyyhkyt"},
		{"species":"Turkinkyyhky","order":"Kyyhkylinnut","family":"Kyyhkyt"},
		{"species":"Turturikyyhky","order":"Kyyhkylinnut","family":"Kyyhkyt"},
		{"species":"Idänturturikyyhky","order":"Kyyhkylinnut","family":"Kyyhkyt"},
		{"species":"Harakkakäki","order":"Käkilinnut","family":"Käet"},
		{"species":"Käki","order":"Käkilinnut","family":"Käet"},
		{"species":"Idänkäki","order":"Käkilinnut","family":"Käet"},
		{"species":"Tornipöllö","order":"Pöllölinnut","family":"Tornipöllöt"},
		{"species":"Kyläpöllönen","order":"Pöllölinnut","family":"Pöllöt"},
		{"species":"Huuhkaja","order":"Pöllölinnut","family":"Pöllöt"},
		{"species":"Tunturipöllö","order":"Pöllölinnut","family":"Pöllöt"},
		{"species":"Hiiripöllö","order":"Pöllölinnut","family":"Pöllöt"},
		{"species":"Varpuspöllö","order":"Pöllölinnut","family":"Pöllöt"},
		{"species":"Minervanpöllö","order":"Pöllölinnut","family":"Pöllöt"},
		{"species":"Lehtopöllö","order":"Pöllölinnut","family":"Pöllöt"},
		{"species":"Viirupöllö","order":"Pöllölinnut","family":"Pöllöt"},
		{"species":"Lapinpöllö","order":"Pöllölinnut","family":"Pöllöt"},
		{"species":"Sarvipöllö","order":"Pöllölinnut","family":"Pöllöt"},
		{"species":"Suopöllö","order":"Pöllölinnut","family":"Pöllöt"},
		{"species":"Helmipöllö","order":"Pöllölinnut","family":"Pöllöt"},
		{"species":"Kehrääjä","order":"Kehrääjälinnut","family":"Kehrääjät"},
		{"species":"Piikkipyrstökiitäjä","order":"Kirskulinnut","family":"Kiitäjät"},
		{"species":"Tervapääsky","order":"Kirskulinnut","family":"Kiitäjät"},
		{"species":"Vaaleakiitäjä","order":"Kirskulinnut","family":"Kiitäjät"},
		{"species":"Alppikiitäjä","order":"Kirskulinnut","family":"Kiitäjät"},
		{"species":"Häätökiitäjä","order":"Kirskulinnut","family":"Kiitäjät"},
		{"species":"Kuningaskalastaja","order":"Säihkylinnut","family":"Kuningaskalastajat"},
		{"species":"Mehiläissyöjä","order":"Säihkylinnut","family":"Mehiläissyöjät"},
		{"species":"Vihermehiläissyöjä","order":"Säihkylinnut","family":"Mehiläissyöjät"},
		{"species":"Sininärhi","order":"Säihkylinnut","family":"Säihkynärhet"},
		{"species":"Harjalintu","order":"Säihkylinnut","family":"Harjalinnut"},
		{"species":"Käenpiika","order":"Tikkalinnut","family":"Tikat"},
		{"species":"Harmaapäätikka","order":"Tikkalinnut","family":"Tikat"},
		{"species":"Vihertikka","order":"Tikkalinnut","family":"Tikat"},
		{"species":"Palokärki","order":"Tikkalinnut","family":"Tikat"},
		{"species":"Käpytikka","order":"Tikkalinnut","family":"Tikat"},
		{"species":"Tammitikka","order":"Tikkalinnut","family":"Tikat"},
		{"species":"Valkoselkätikka","order":"Tikkalinnut","family":"Tikat"},
		{"species":"Pikkutikka","order":"Tikkalinnut","family":"Tikat"},
		{"species":"Pohjantikka","order":"Tikkalinnut","family":"Tikat"},
		{"species":"Arokiuru","order":"Varpuslinnut","family":"Kiurut"},
		{"species":"Ylänkökiuru","order":"Varpuslinnut","family":"Kiurut"},
		{"species":"Valkosiipikiuru","order":"Varpuslinnut","family":"Kiurut"},
		{"species":"Mustakiuru","order":"Varpuslinnut","family":"Kiurut"},
		{"species":"Lyhytvarvaskiuru","order":"Varpuslinnut","family":"Kiurut"},
		{"species":"Pikkukiuru","order":"Varpuslinnut","family":"Kiurut"},
		{"species":"Töyhtökiuru","order":"Varpuslinnut","family":"Kiurut"},
		{"species":"Kangaskiuru","order":"Varpuslinnut","family":"Kiurut"},
		{"species":"Kiuru","order":"Varpuslinnut","family":"Kiurut"},
		{"species":"Tunturikiuru","order":"Varpuslinnut","family":"Kiurut"},
		{"species":"Törmäpääsky","order":"Varpuslinnut","family":"Pääskyt"},
		{"species":"Kalliopääsky","order":"Varpuslinnut","family":"Pääskyt"},
		{"species":"Haarapääsky","order":"Varpuslinnut","family":"Pääskyt"},
		{"species":"Räystäspääsky","order":"Varpuslinnut","family":"Pääskyt"},
		{"species":"Ruostepääsky","order":"Varpuslinnut","family":"Pääskyt"},
		{"species":"Isokirvinen","order":"Varpuslinnut","family":"Västäräkit"},
		{"species":"Mongoliankirvinen","order":"Varpuslinnut","family":"Västäräkit"},
		{"species":"Nummikirvinen","order":"Varpuslinnut","family":"Västäräkit"},
		{"species":"Taigakirvinen","order":"Varpuslinnut","family":"Västäräkit"},
		{"species":"Metsäkirvinen","order":"Varpuslinnut","family":"Västäräkit"},
		{"species":"Tundrakirvinen","order":"Varpuslinnut","family":"Västäräkit"},
		{"species":"Niittykirvinen","order":"Varpuslinnut","family":"Västäräkit"},
		{"species":"Lapinkirvinen","order":"Varpuslinnut","family":"Västäräkit"},
		{"species":"Luotokirvinen","order":"Varpuslinnut","family":"Västäräkit"},
		{"species":"Keltavästäräkki","order":"Varpuslinnut","family":"Västäräkit"},
		{"species":"Sitruunavästäräkki","order":"Varpuslinnut","family":"Västäräkit"},
		{"species":"Virtavästäräkki","order":"Varpuslinnut","family":"Västäräkit"},
		{"species":"Västäräkki","order":"Varpuslinnut","family":"Västäräkit"},
		{"species":"Tilhi","order":"Varpuslinnut","family":"Tilhet"},
		{"species":"Koskikara","order":"Varpuslinnut","family":"Koskikarat"},
		{"species":"Peukaloinen","order":"Varpuslinnut","family":"Peukaloiset"},
		{"species":"Rautiainen","order":"Varpuslinnut","family":"Rautiaiset"},
		{"species":"Taigarautiainen","order":"Varpuslinnut","family":"Rautiaiset"},
		{"species":"Mustakurkkurautiainen","order":"Varpuslinnut","family":"Rautiaiset"},
		{"species":"Alppirautiainen","order":"Varpuslinnut","family":"Rautiaiset"},
		{"species":"Ruostepyrstö","order":"Varpuslinnut","family":"Rastaat"},
		{"species":"Punarinta","order":"Varpuslinnut","family":"Rastaat"},
		{"species":"Satakieli","order":"Varpuslinnut","family":"Rastaat"},
		{"species":"Etelänsatakieli","order":"Varpuslinnut","family":"Rastaat"},
		{"species":"Sinirinta","order":"Varpuslinnut","family":"Rastaat"},
		{"species":"Rubiinisatakieli","order":"Varpuslinnut","family":"Rastaat"},
		{"species":"Sinipyrstö","order":"Varpuslinnut","family":"Rastaat"},
		{"species":"Mustaleppälintu","order":"Varpuslinnut","family":"Rastaat"},
		{"species":"Leppälintu","order":"Varpuslinnut","family":"Rastaat"},
		{"species":"Pensastasku","order":"Varpuslinnut","family":"Rastaat"},
		{"species":"Nokitasku","order":"Varpuslinnut","family":"Rastaat"},
		{"species":"Sepeltasku","order":"Varpuslinnut","family":"Rastaat"},
		{"species":"Mustapäätasku","order":"Varpuslinnut","family":"Rastaat"},
		{"species":"Arotasku","order":"Varpuslinnut","family":"Rastaat"},
		{"species":"Kivitasku","order":"Varpuslinnut","family":"Rastaat"},
		{"species":"Nunnatasku","order":"Varpuslinnut","family":"Rastaat"},
		{"species":"Rusotasku","order":"Varpuslinnut","family":"Rastaat"},
		{"species":"Aavikkotasku","order":"Varpuslinnut","family":"Rastaat"},
		{"species":"Kivikkorastas","order":"Varpuslinnut","family":"Rastaat"},
		{"species":"Sinirastas","order":"Varpuslinnut","family":"Rastaat"},
		{"species":"Kirjorastas","order":"Varpuslinnut","family":"Rastaat"},
		{"species":"Korpirastas","order":"Varpuslinnut","family":"Rastaat"},
		{"species":"Sepelrastas","order":"Varpuslinnut","family":"Rastaat"},
		{"species":"Mustarastas","order":"Varpuslinnut","family":"Rastaat"},
		{"species":"Harmaakurkkurastas","order":"Varpuslinnut","family":"Rastaat"},
		{"species":"Ruosterastas","order":"Varpuslinnut","family":"Rastaat"},
		{"species":"Ruostesiipirastas","order":"Varpuslinnut","family":"Rastaat"},
		{"species":"Mustakaularastas","order":"Varpuslinnut","family":"Rastaat"},
		{"species":"Räkättirastas","order":"Varpuslinnut","family":"Rastaat"},
		{"species":"Laulurastas","order":"Varpuslinnut","family":"Rastaat"},
		{"species":"Punakylkirastas","order":"Varpuslinnut","family":"Rastaat"},
		{"species":"Kulorastas","order":"Varpuslinnut","family":"Rastaat"},
		{"species":"Sarasirkkalintu","order":"Varpuslinnut","family":"Kertut"},
		{"species":"Viirusirkkalintu","order":"Varpuslinnut","family":"Kertut"},
		{"species":"Pensassirkkalintu","order":"Varpuslinnut","family":"Kertut"},
		{"species":"Viitasirkkalintu","order":"Varpuslinnut","family":"Kertut"},
		{"species":"Ruokosirkkalintu","order":"Varpuslinnut","family":"Kertut"},
		{"species":"Paksunokkakerttunen","order":"Varpuslinnut","family":"Kertut"},
		{"species":"Pikkukultarinta","order":"Varpuslinnut","family":"Kertut"},
		{"species":"Aavikkokultarinta","order":"Varpuslinnut","family":"Kertut"},
		{"species":"Vaaleakultarinta","order":"Varpuslinnut","family":"Kertut"},
		{"species":"Kultarinta","order":"Varpuslinnut","family":"Kertut"},
		{"species":"Sarakerttunen","order":"Varpuslinnut","family":"Kertut"},
		{"species":"Ruokokerttunen","order":"Varpuslinnut","family":"Kertut"},
		{"species":"Kenttäkerttunen","order":"Varpuslinnut","family":"Kertut"},
		{"species":"Viitakerttunen","order":"Varpuslinnut","family":"Kertut"},
		{"species":"Luhtakerttunen","order":"Varpuslinnut","family":"Kertut"},
		{"species":"Rytikerttunen","order":"Varpuslinnut","family":"Kertut"},
		{"species":"Rastaskerttunen","order":"Varpuslinnut","family":"Kertut"},
		{"species":"Ruskokerttu","order":"Varpuslinnut","family":"Kertut"},
		{"species":"Rusorintakerttu","order":"Varpuslinnut","family":"Kertut"},
		{"species":"Samettipääkerttu","order":"Varpuslinnut","family":"Kertut"},
		{"species":"Mustakurkkukerttu","order":"Varpuslinnut","family":"Kertut"},
		{"species":"Kääpiökerttu","order":"Varpuslinnut","family":"Kertut"},
		{"species":"Kirjokerttu","order":"Varpuslinnut","family":"Kertut"},
		{"species":"Hernekerttu","order":"Varpuslinnut","family":"Kertut"},
		{"species":"Pensaskerttu","order":"Varpuslinnut","family":"Kertut"},
		{"species":"Lehtokerttu","order":"Varpuslinnut","family":"Kertut"},
		{"species":"Mustapääkerttu","order":"Varpuslinnut","family":"Kertut"},
		{"species":"Amurinuunilintu","order":"Varpuslinnut","family":"Kertut"},
		{"species":"Kaukasianuunilintu","order":"Varpuslinnut","family":"Kertut"},
		{"species":"Burjatianuunilintu","order":"Varpuslinnut","family":"Kertut"},
		{"species":"Idänuunilintu","order":"Varpuslinnut","family":"Kertut"},
		{"species":"Lapinuunilintu","order":"Varpuslinnut","family":"Kertut"},
		{"species":"Hippiäisuunilintu","order":"Varpuslinnut","family":"Kertut"},
		{"species":"Taigauunilintu","order":"Varpuslinnut","family":"Kertut"},
		{"species":"Kashmirinuunilintu","order":"Varpuslinnut","family":"Kertut"},
		{"species":"Siperianuunilintu","order":"Varpuslinnut","family":"Kertut"},
		{"species":"Ruskouunilintu","order":"Varpuslinnut","family":"Kertut"},
		{"species":"Vuoriuunilintu","order":"Varpuslinnut","family":"Kertut"},
		{"species":"Balkaninuunilintu","order":"Varpuslinnut","family":"Kertut"},
		{"species":"Sirittäjä","order":"Varpuslinnut","family":"Kertut"},
		{"species":"Tiltaltti","order":"Varpuslinnut","family":"Kertut"},
		{"species":"Iberiantiltaltti","order":"Varpuslinnut","family":"Kertut"},
		{"species":"Pajulintu","order":"Varpuslinnut","family":"Kertut"},
		{"species":"Hippiäinen","order":"Varpuslinnut","family":"Kertut"},
		{"species":"Tulipäähippiäinen","order":"Varpuslinnut","family":"Kertut"},
		{"species":"Harmaasieppo","order":"Varpuslinnut","family":"Siepot"},
		{"species":"Pikkusieppo","order":"Varpuslinnut","family":"Siepot"},
		{"species":"Idänpikkusieppo","order":"Varpuslinnut","family":"Siepot"},
		{"species":"Sepelsieppo","order":"Varpuslinnut","family":"Siepot"},
		{"species":"Kirjosieppo","order":"Varpuslinnut","family":"Siepot"},
		{"species":"Viiksitimali","order":"Varpuslinnut","family":"Timalit"},
		{"species":"Pyrstötiainen","order":"Varpuslinnut","family":"Pyrstötiaiset"},
		{"species":"Valkopäätiainen","order":"Varpuslinnut","family":"Tiaiset"},
		{"species":"Sinitiainen","order":"Varpuslinnut","family":"Tiaiset"},
		{"species":"Talitiainen","order":"Varpuslinnut","family":"Tiaiset"},
		{"species":"Kuusitiainen","order":"Varpuslinnut","family":"Tiaiset"},
		{"species":"Töyhtötiainen","order":"Varpuslinnut","family":"Tiaiset"},
		{"species":"Viitatiainen","order":"Varpuslinnut","family":"Tiaiset"},
		{"species":"Hömötiainen","order":"Varpuslinnut","family":"Tiaiset"},
		{"species":"Lapintiainen","order":"Varpuslinnut","family":"Tiaiset"},
		{"species":"Pähkinänakkeli","order":"Varpuslinnut","family":"Pähkinänakkelit"},
		{"species":"Puukiipijä","order":"Varpuslinnut","family":"Puukiipijät"},
		{"species":"Pussitiainen","order":"Varpuslinnut","family":"Pussitiaiset"},
		{"species":"Kuhankeittäjä","order":"Varpuslinnut","family":"Kuhankeittäjät"},
		{"species":"Punapyrstölepinkäinen","order":"Varpuslinnut","family":"Lepinkäiset"},
		{"species":"Pikkulepinkäinen","order":"Varpuslinnut","family":"Lepinkäiset"},
		{"species":"Mustaotsalepinkäinen","order":"Varpuslinnut","family":"Lepinkäiset"},
		{"species":"Isolepinkäinen","order":"Varpuslinnut","family":"Lepinkäiset"},
		{"species":"Etelänisolepinkäinen","order":"Varpuslinnut","family":"Lepinkäiset"},
		{"species":"Punapäälepinkäinen","order":"Varpuslinnut","family":"Lepinkäiset"},
		{"species":"Valko-otsalepinkäinen","order":"Varpuslinnut","family":"Lepinkäiset"},
		{"species":"Närhi","order":"Varpuslinnut","family":"Varikset"},
		{"species":"Kuukkeli","order":"Varpuslinnut","family":"Varikset"},
		{"species":"Harakka","order":"Varpuslinnut","family":"Varikset"},
		{"species":"Pähkinähakki","order":"Varpuslinnut","family":"Varikset"},
		{"species":"Naakka","order":"Varpuslinnut","family":"Varikset"},
		{"species":"Idännaakka","order":"Varpuslinnut","family":"Varikset"},
		{"species":"Mustavaris","order":"Varpuslinnut","family":"Varikset"},
		{"species":"Varis","order":"Varpuslinnut","family":"Varikset"},
		{"species":"Korppi","order":"Varpuslinnut","family":"Varikset"},
		{"species":"Kottarainen","order":"Varpuslinnut","family":"Kottaraiset"},
		{"species":"Punakottarainen","order":"Varpuslinnut","family":"Kottaraiset"},
		{"species":"Varpunen","order":"Varpuslinnut","family":"Varpuset"},
		{"species":"Pensasvarpunen","order":"Varpuslinnut","family":"Varpuset"},
		{"species":"Pikkuvarpunen","order":"Varpuslinnut","family":"Varpuset"},
		{"species":"Peippo","order":"Varpuslinnut","family":"Peipot"},
		{"species":"Järripeippo","order":"Varpuslinnut","family":"Peipot"},
		{"species":"Keltahemppo","order":"Varpuslinnut","family":"Peipot"},
		{"species":"Viherpeippo","order":"Varpuslinnut","family":"Peipot"},
		{"species":"Tikli","order":"Varpuslinnut","family":"Peipot"},
		{"species":"Vihervarpunen","order":"Varpuslinnut","family":"Peipot"},
		{"species":"Hemppo","order":"Varpuslinnut","family":"Peipot"},
		{"species":"Vuorihemppo","order":"Varpuslinnut","family":"Peipot"},
		{"species":"Urpiainen","order":"Varpuslinnut","family":"Peipot"},
		{"species":"Tundraurpiainen","order":"Varpuslinnut","family":"Peipot"},
		{"species":"Kirjosiipikäpylintu","order":"Varpuslinnut","family":"Peipot"},
		{"species":"Pikkukäpylintu","order":"Varpuslinnut","family":"Peipot"},
		{"species":"Isokäpylintu","order":"Varpuslinnut","family":"Peipot"},
		{"species":"Aavikkotulkku","order":"Varpuslinnut","family":"Peipot"},
		{"species":"Punavarpunen","order":"Varpuslinnut","family":"Peipot"},
		{"species":"Taviokuurna","order":"Varpuslinnut","family":"Peipot"},
		{"species":"Punatulkku","order":"Varpuslinnut","family":"Peipot"},
		{"species":"Nokkavarpunen","order":"Varpuslinnut","family":"Peipot"},
		{"species":"Viirukerttuli","order":"Varpuslinnut","family":"kerttulit"},
		{"species":"Kettusirkku","order":"Varpuslinnut","family":"Sirkut"},
		{"species":"Valkokurkkusirkku","order":"Varpuslinnut","family":"Sirkut"},
		{"species":"Lapinsirkku","order":"Varpuslinnut","family":"Sirkut"},
		{"species":"Pulmunen","order":"Varpuslinnut","family":"Sirkut"},
		{"species":"Harmaapääsirkku","order":"Varpuslinnut","family":"Sirkut"},
		{"species":"Mäntysirkku","order":"Varpuslinnut","family":"Sirkut"},
		{"species":"Keltasirkku","order":"Varpuslinnut","family":"Sirkut"},
		{"species":"Peltosirkku","order":"Varpuslinnut","family":"Sirkut"},
		{"species":"Kivikkosirkku","order":"Varpuslinnut","family":"Sirkut"},
		{"species":"Ruostekurkkusirkku","order":"Varpuslinnut","family":"Sirkut"},
		{"species":"Pohjansirkku","order":"Varpuslinnut","family":"Sirkut"},
		{"species":"Pikkusirkku","order":"Varpuslinnut","family":"Sirkut"},
		{"species":"Kastanjasirkku","order":"Varpuslinnut","family":"Sirkut"},
		{"species":"Kultasirkku","order":"Varpuslinnut","family":"Sirkut"},
		{"species":"Pajusirkku","order":"Varpuslinnut","family":"Sirkut"},
		{"species":"Mustapääsirkku","order":"Varpuslinnut","family":"Sirkut"},
		{"species":"Harmaasirkku","order":"Varpuslinnut","family":"Sirkut"},
		{"species":"Mustajoutsen","order":"Sorsalinnut","family":"Sorsat"},
		{"species":"Joutsenhanhi","order":"Sorsalinnut","family":"Sorsat"},
		{"species":"Tiibetinhanhi","order":"Sorsalinnut","family":"Sorsat"},
		{"species":"Eskimohanhi","order":"Sorsalinnut","family":"Sorsat"},
		{"species":"Afrikanhanhi","order":"Sorsalinnut","family":"Sorsat"},
		{"species":"Morsiosorsa","order":"Sorsalinnut","family":"Sorsat"},
		{"species":"Patagonianhaapana","order":"Sorsalinnut","family":"Sorsat"},
		{"species":"Sirppisorsa","order":"Sorsalinnut","family":"Sorsat"},
		{"species":"Siperiantavi","order":"Sorsalinnut","family":"Sorsat"},
		{"species":"Valkoposkisorsa","order":"Sorsalinnut","family":"Sorsat"},
		{"species":"Punatavi","order":"Sorsalinnut","family":"Sorsat"},
		{"species":"Pikkutelkkä","order":"Sorsalinnut","family":"Sorsat"},
		{"species":"Harjakoskelo","order":"Sorsalinnut","family":"Sorsat"},
		{"species":"Kiinanriisihaikara","order":"Haikaralinnut","family":"Haikarat"},
		{"species":"Intianriisihaikara","order":"Haikaralinnut","family":"Haikarat"},
		{"species":"Savannihaikara","order":"Haikaralinnut","family":"Kattohaikarat"},
		{"species":"Flamingo","order":"Flamingolinnut","family":"Flamingot"},
		{"species":"Chilenflamingo","order":"Flamingolinnut","family":"Flamingot"},
		{"species":"Pikkuflamingo","order":"Flamingolinnut","family":"Flamingot"},
		{"species":"Kuningasmerikotka","order":"Päiväpetolinnut","family":"Haukat"},
		{"species":"Palmukyyhky","order":"Kyyhkylinnut","family":"Kyyhkyt"},
		{"species":"Jakobiinikäki","order":"Käkilinnut","family":"Käet"},
		{"species":"Vuorileppälintu","order":"Varpuslinnut","family":"Rastaat"},
		{"species":"Kiinankottarainen","order":"Varpuslinnut","family":"Kottaraiset"},
		{"species":"Viirupääkottarainen","order":"Varpuslinnut","family":"Kottaraiset"},
		{"species":"Pihamaina","order":"Varpuslinnut","family":"Kottaraiset"},
		{"species":"Sitruunahemppo","order":"Varpuslinnut","family":"Peipot"},
		{"species":"Pyrstötulkku","order":"Varpuslinnut","family":"Peipot"},
		{"species":"Japaninnokkavarpunen","order":"Varpuslinnut","family":"Peipot"},
		{"species":"Niittysirkku","order":"Varpuslinnut","family":"Sirkut"},
		{"species":"Kultatöyhtösirkku","order":"Varpuslinnut","family":"Sirkut"},
		{"species":"Ruskopääsirkku","order":"Varpuslinnut","family":"Sirkut"},
		{"species":"Indigokardinaali","order":"Varpuslinnut","family":"Sirkut"},
		{"species":"Turkoosikardinaali","order":"Varpuslinnut","family":"Sirkut"},
		{"species":"Sateenkaarikardinaali","order":"Varpuslinnut","family":"Sirkut"},
		{"species":"Kesykyyhky","order":"Kyyhkylinnut","family":"Kyyhkyt"}
	]
}
